netfl/__init__.py
netfl/core/client.py
netfl/core/experiment.py
netfl/core/models.py
netfl/core/partitioners.py
netfl/core/server.py
netfl/core/task.py
netfl/core/worker.py
netfl/utils/initializer.py
netfl/utils/log.py
netfl/utils/metrics.py
netfl/utils/net.py
netfl/utils/resources.py
netfl/utils/runner.py
netfl-1.5.0.dist-info/METADATA
netfl-1.5.0.dist-info/WHEEL
netfl-1.5.0.dist-info/entry_points.txt
netfl-1.5.0.dist-info/licenses/LICENSE
netfl-1.5.0.dist-info/RECORD
