Metadata-Version: 2.4
Name: netfl
Version: 1.5.0
Summary: NetFL is a framework for running Federated Learning (FL) experiments in simulated IoT and Fog/Edge computing environments, with support for heterogeneous devices and configurable network conditions.
Project-URL: Homepage, https://github.com/larsid/netfl
License: Apache License 2.0
License-File: LICENSE
Keywords: edge-computing,federated-learning,fog-computing,iot
Classifier: Development Status :: 4 - Beta
Classifier: Intended Audience :: Developers
Classifier: Intended Audience :: Science/Research
Classifier: License :: OSI Approved :: Apache Software License
Classifier: Programming Language :: Python :: 3.9
Classifier: Topic :: Scientific/Engineering :: Artificial Intelligence
Classifier: Topic :: System :: Distributed Computing
Requires-Python: >=3.9
Requires-Dist: clusternet>=0.9.3
Requires-Dist: flwr-datasets[vision]==0.5.0
Requires-Dist: flwr==1.11.0
Requires-Dist: fogbed>=1.2.0
Requires-Dist: psutil>=7.1.3
Requires-Dist: tensorflow-cpu==2.17.0
